LICENSE
README.md
setup.cfg
setup.py
espncricket/ESPN.py
espncricket/__init__.py
espncricket/multithreading_utilities/MultiThread.py
espncricket/multithreading_utilities/__init__.py
espncricket/request_utilities/Request.py
espncricket/request_utilities/__init__.py
iua.egg-info/PKG-INFO
iua.egg-info/SOURCES.txt
iua.egg-info/dependency_links.txt
iua.egg-info/requires.txt
iua.egg-info/top_level.txt