Metadata-Version: 2.1
Name: iua
Version: 0.0.9
Summary: ESPN Cricinfo Scraper
Home-page: https://github.com/SanketPatole/ESPN-Statsguru-Scraper
Author: Sanket Patole
Author-email: snkt.pat2@gmail.com
License: UNKNOWN
Project-URL: Bug Reports, https://github.com/SanketPatole/ESPN-Statsguru-Scraper/issues
Project-URL: Funding, https://donate.pypi.org
Project-URL: Say Thanks!, http://saythanks.io/to/example
Project-URL: Source, https://github.com/SanketPatole/ESPN-Statsguru-Scraper/
Keywords: iua
Platform: UNKNOWN
Classifier: Development Status :: 3 - Alpha
Classifier: Intended Audience :: Developers
Classifier: Topic :: Software Development :: Build Tools
Classifier: License :: OSI Approved :: MIT License
Classifier: Programming Language :: Python :: 3
Classifier: Programming Language :: Python :: 3.7
Classifier: Programming Language :: Python :: 3.8
Classifier: Programming Language :: Python :: 3.9
Classifier: Programming Language :: Python :: 3.10
Classifier: Programming Language :: Python :: 3 :: Only
Requires-Python: >=3.6, <4
License-File: LICENSE
